sarada/__init__.py
sarada/meta.py
sarada-0.2.0.dist-info/METADATA
sarada-0.2.0.dist-info/WHEEL
sarada-0.2.0.dist-info/RECORD
