Metadata-Version: 2.4
Name: sarada
Version: 0.2.0
Summary: Add your description here
Requires-Python: >=3.12
Requires-Dist: jyotisha>=0.1.2
Requires-Dist: pyswisseph>=2.10.3.2
